Workbook

Sheet Resumen Ejecutivo
A1: E-COMMERCE & LOGISTICS — RESUMEN EJECUTIVO
A2: Fuente: hojas DATOS_Olist_Mensual, DATOS_Categorías, DATOS_Logística, DATOS_Pagos_Status, DATOS_DataCo
B4: TOTAL PEDIDOS | D4: REVENUE TOTAL | F4: TICKET MEDIO | H4: REVIEW SCORE MEDIO | J4: % ENTREGAS A TIEMPO | L4: % PEDIDOS TARDÍOS
B5: =SUM(DATOS_Olist_Mensual!C4:C29) -> 58800 | D5: =SUM(DATOS_Olist_Mensual!D4:D29) -> 5200158.9 | F5: =SUMPRODUCT(DATOS_Olist_Mensual!C4:C29,DATOS_Olist_Mensual!E4:E29)/SUM(DATOS_Olist_Mensual!C4:C29) -> 76.918415 | H5: =SUMPRODUCT(DATOS_Olist_Mensual!C4:C29,DATOS_Olist_Mensual!F4:F29)/SUM(DATOS_Olist_Mensual!C4:C29) -> 4.05241 | J5: =1-AVERAGE(DATOS_Logística!C4:C23) -> 0.8855 | L5: =AVERAGE(DATOS_Logística!C4:C23) -> 0.1145
B6: pedidos totales | D6: € acumulados | F6: € por pedido | H6: sobre 5 estrellas | J6: pedidos entregados | L6: tasa retraso media
B8: TOP CATEGORÍAS POR REVENUE (fuente: DATOS_Categorías) | I8: ESTADO DE PEDIDOS (fuente: DATOS_Pagos_Status!H:K)
B9: Categoría | C9: Pedidos | D9: Revenue (€) | E9: % s/Total | F9: Ticket (€) | G9: Review | I9: Estado | J9: Pedidos | K9: Revenue (€) | L9: % Pedidos | M9: Ticket (€)
B10: =DATOS_Categorías!A4 -> Eletronicos | C10: =DATOS_Categorías!B4 -> 3323 | D10: =DATOS_Categorías!C4 -> 302109.4 | E10: =DATOS_Categorías!C4/SUM(DATOS_Categorías!C$4:C$21) -> 0.058096186 | F10: =DATOS_Categorías!D4 -> 78.91 | G10: =DATOS_Categorías!F4 -> 4.04 | I10: =DATOS_Pagos_Status!H4 -> delivered | J10: =DATOS_Pagos_Status!I4 -> 45192 | K10: =DATOS_Pagos_Status!J4 -> 4005198.9 | L10: =DATOS_Pagos_Status!I4/SUM(DATOS_Pagos_Status!I$4:I$11) -> 0.76857143 | M10: =DATOS_Pagos_Status!K4 -> 77.09
B11: =DATOS_Categorías!A5 -> Livros Tecnicos | C11: =DATOS_Categorías!B5 -> 3308 | D11: =DATOS_Categorías!C5 -> 301994.9 | E11: =DATOS_Categorías!C5/SUM(DATOS_Categorías!C$4:C$21) -> 0.058074168 | F11: =DATOS_Categorías!D5 -> 79.43 | G11: =DATOS_Categorías!F5 -> 4.05 | I11: =DATOS_Pagos_Status!H5 -> shipped | J11: =DATOS_Pagos_Status!I5 -> 4815 | K11: =DATOS_Pagos_Status!J5 -> 424746.62 | L11: =DATOS_Pagos_Status!I5/SUM(DATOS_Pagos_Status!I$4:I$11) -> 0.081887755 | M11: =DATOS_Pagos_Status!K5 -> 76.68
B12: =DATOS_Categorías!A6 -> Musica | C12: =DATOS_Categorías!B6 -> 3367 | D12: =DATOS_Categorías!C6 -> 300432.59 | E12: =DATOS_Categorías!C6/SUM(DATOS_Categorías!C$4:C$21) -> 0.057773733 | F12: =DATOS_Categorías!D6 -> 77.6 | G12: =DATOS_Categorías!F6 -> 4.06 | I12: =DATOS_Pagos_Status!H6 -> canceled | J12: =DATOS_Pagos_Status!I6 -> 3503 | K12: =DATOS_Pagos_Status!J6 -> 306739.25 | L12: =DATOS_Pagos_Status!I6/SUM(DATOS_Pagos_Status!I$4:I$11) -> 0.05957483 | M12: =DATOS_Pagos_Status!K6 -> 76.29
B13: =DATOS_Categorías!A7 -> Relogios Presentes | C13: =DATOS_Categorías!B7 -> 3365 | D13: =DATOS_Categorías!C7 -> 296836.12 | E13: =DATOS_Categorías!C7/SUM(DATOS_Categorías!C$4:C$21) -> 0.057082125 | F13: =DATOS_Categorías!D7 -> 76.7 | G13: =DATOS_Categorías!F7 -> 4.05 | I13: =DATOS_Pagos_Status!H7 -> unavailable | J13: =DATOS_Pagos_Status!I7 -> 1750 | K13: =DATOS_Pagos_Status!J7 -> 148938.12 | L13: =DATOS_Pagos_Status!I7/SUM(DATOS_Pagos_Status!I$4:I$11) -> 0.029761905 | M13: =DATOS_Pagos_Status!K7 -> 74
B14: =DATOS_Categorías!A8 -> Pet Shop | C14: =DATOS_Categorías!B8 -> 3270 | D14: =DATOS_Categorías!C8 -> 292351.49 | E14: =DATOS_Categorías!C8/SUM(DATOS_Categorías!C$4:C$21) -> 0.056219722 | F14: =DATOS_Categorías!D8 -> 77.66 | G14: =DATOS_Categorías!F8 -> 4.1 | I14: =DATOS_Pagos_Status!H8 -> processing | J14: =DATOS_Pagos_Status!I8 -> 1198 | K14: =DATOS_Pagos_Status!J8 -> 107739.62 | L14: =DATOS_Pagos_Status!I8/SUM(DATOS_Pagos_Status!I$4:I$11) -> 0.02037415 | M14: =DATOS_Pagos_Status!K8 -> 78.22
B15: =DATOS_Categorías!A9 -> Cama Mesa Banho | C15: =DATOS_Categorías!B9 -> 3291 | D15: =DATOS_Categorías!C9 -> 291349.63 | E15: =DATOS_Categorías!C9/SUM(DATOS_Categorías!C$4:C$21) -> 0.056027063 | F15: =DATOS_Categorías!D9 -> 76.97 | G15: =DATOS_Categorías!F9 -> 4.05 | I15: =DATOS_Pagos_Status!H9 -> invoiced | J15: =DATOS_Pagos_Status!I9 -> 1192 | K15: =DATOS_Pagos_Status!J9 -> 103034.19 | L15: =DATOS_Pagos_Status!I9/SUM(DATOS_Pagos_Status!I$4:I$11) -> 0.020272109 | M15: =DATOS_Pagos_Status!K9 -> 75.04
B16: =DATOS_Categorías!A10 -> Bebes | C16: =DATOS_Categorías!B10 -> 3261 | D16: =DATOS_Categorías!C10 -> 290927.46 | E16: =DATOS_Categorías!C10/SUM(DATOS_Categorías!C$4:C$21) -> 0.055945879 | F16: =DATOS_Categorías!D10 -> 77.6 | G16: =DATOS_Categorías!F10 -> 4.06 | I16: =DATOS_Pagos_Status!H10 -> approved | J16: =DATOS_Pagos_Status!I10 -> 601 | K16: =DATOS_Pagos_Status!J10 -> 54981.01 | L16: =DATOS_Pagos_Status!I10/SUM(DATOS_Pagos_Status!I$4:I$11) -> 0.010221088 | M16: =DATOS_Pagos_Status!K10 -> 79.33
B17: =DATOS_Categorías!A11 -> Informatica Acessorios | C17: =DATOS_Categorías!B11 -> 3331 | D17: =DATOS_Categorías!C11 -> 289943.56 | E17: =DATOS_Categorías!C11/SUM(DATOS_Categorías!C$4:C$21) -> 0.055756673 | F17: =DATOS_Categorías!D11 -> 75.61 | G17: =DATOS_Categorías!F11 -> 4.06 | I17: =DATOS_Pagos_Status!H11 -> created | J17: =DATOS_Pagos_Status!I11 -> 549 | K17: =DATOS_Pagos_Status!J11 -> 48781.19 | L17: =DATOS_Pagos_Status!I11/SUM(DATOS_Pagos_Status!I$4:I$11) -> 0.0093367347 | M17: =DATOS_Pagos_Status!K11 -> 77.04
B18: =DATOS_Categorías!A12 -> Perfumaria | C18: =DATOS_Categorías!B12 -> 3251 | D18: =DATOS_Categorías!C12 -> 288491.97 | E18: =DATOS_Categorías!C12/SUM(DATOS_Categorías!C$4:C$21) -> 0.05547753 | F18: =DATOS_Categorías!D12 -> 77.25 | G18: =DATOS_Categorías!F12 -> 4.02
B19: =DATOS_Categorías!A13 -> Construcao Ferramentas | C19: =DATOS_Categorías!B13 -> 3225 | D19: =DATOS_Categorías!C13 -> 288174.33 | E19: =DATOS_Categorías!C13/SUM(DATOS_Categorías!C$4:C$21) -> 0.055416447 | F19: =DATOS_Categorías!D13 -> 77.63 | G19: =DATOS_Categorías!F13 -> 4.02
B20: =DATOS_Categorías!A14 -> Utilidades Domesticas | C20: =DATOS_Categorías!B14 -> 3319 | D20: =DATOS_Categorías!C14 -> 287548.46 | E20: =DATOS_Categorías!C14/SUM(DATOS_Categorías!C$4:C$21) -> 0.055296091 | F20: =DATOS_Categorías!D14 -> 75.35 | G20: =DATOS_Categorías!F14 -> 4.04
B21: =DATOS_Categorías!A15 -> Ferramentas Jardim | C21: =DATOS_Categorías!B15 -> 3220 | D21: =DATOS_Categorías!C15 -> 286743.07 | E21: =DATOS_Categorías!C15/SUM(DATOS_Categorías!C$4:C$21) -> 0.055141213 | F21: =DATOS_Categorías!D15 -> 77.62 | G21: =DATOS_Categorías!F15 -> 4.05
B22: =DATOS_Categorías!A16 -> Cool Stuff | C22: =DATOS_Categorías!B16 -> 3242 | D22: =DATOS_Categorías!C16 -> 285465.85 | E22: =DATOS_Categorías!C16/SUM(DATOS_Categorías!C$4:C$21) -> 0.054895601 | F22: =DATOS_Categorías!D16 -> 76.66 | G22: =DATOS_Categorías!F16 -> 4.08
B23: =DATOS_Categorías!A17 -> Brinquedos | C23: =DATOS_Categorías!B17 -> 3238 | D23: =DATOS_Categorías!C17 -> 285047.76 | E23: =DATOS_Categorías!C17/SUM(DATOS_Categorías!C$4:C$21) -> 0.054815202 | F23: =DATOS_Categorías!D17 -> 76.55 | G23: =DATOS_Categorías!F17 -> 4.07
B24: =DATOS_Categorías!A18 -> Beleza Saude | C24: =DATOS_Categorías!B18 -> 3232 | D24: =DATOS_Categorías!C18 -> 281715.32 | E24: =DATOS_Categorías!C18/SUM(DATOS_Categorías!C$4:C$21) -> 0.054174368 | F24: =DATOS_Categorías!D18 -> 75.92 | G24: =DATOS_Categorías!F18 -> 4.03
B25: =DATOS_Categorías!A19 -> Automotivo | C25: =DATOS_Categorías!B19 -> 3221 | D25: =DATOS_Categorías!C19 -> 281289.68 | E25: =DATOS_Categorías!C19/SUM(DATOS_Categorías!C$4:C$21) -> 0.054092516 | F25: =DATOS_Categorías!D19 -> 76.02 | G25: =DATOS_Categorías!F19 -> 4.05
B26: =DATOS_Categorías!A20 -> Esporte Lazer | C26: =DATOS_Categorías!B20 -> 3185 | D26: =DATOS_Categorías!C20 -> 277805.33 | E26: =DATOS_Categorías!C20/SUM(DATOS_Categorías!C$4:C$21) -> 0.053422469 | F26: =DATOS_Categorías!D20 -> 75.87 | G26: =DATOS_Categorías!F20 -> 4.07
B27: =DATOS_Categorías!A21 -> Moveis Decoracao | C27: =DATOS_Categorías!B21 -> 3151 | D27: =DATOS_Categorías!C21 -> 271931.99 | E27: =DATOS_Categorías!C21/SUM(DATOS_Categorías!C$4:C$21) -> 0.052293015 | F27: =DATOS_Categorías!D21 -> 75.05 | G27: =DATOS_Categorías!F21 -> 4.06

Sheet Análisis Logística
A1: ANÁLISIS DE LOGÍSTICA & ENVÍOS
A2: Fuente: DATOS_Logística (estados Olist, pedidos entregados) + DATOS_DataCo (supply chain)
A4: =SUMPRODUCT(DATOS_Logística!B4:B23*DATOS_Logística!C4:C23)/SUM(DATOS_Logística!B4:B23) -> 0.11833488 | C4: Tasa retraso ponderada | E4: =SUMPRODUCT(DATOS_Logística!B4:B23*DATOS_Logística!E4:E23)/SUM(DATOS_Logística!B4:B23) -> 8.880206
C5: =SUMPRODUCT(DATOS_Logística!B4:B23*DATOS_Logística!D4:D23)/SUM(DATOS_Logística!B4:B23) -> -5.6222203 | E5: Días entrega promedio
C6: Retraso promedio ponderado
A8: Estado | B8: Pedidos | C8: % Tardíos | D8: Retraso Medio (días) | E8: Días Entrega | F8: Review Medio | H8: Modo Envío | I8: Pedidos | J8: % Tardía | K8: Días Real | L8: Días Prog. | M8: Ventas (€) | N8: Profit (€)
A9: =DATOS_Logística!A4 -> AL | B9: =DATOS_Logística!B4 -> 260 | C9: =DATOS_Logística!C4 -> 0.15 | D9: =DATOS_Logística!D4 -> -5.72 | E9: =DATOS_Logística!E4 -> 8.69 | F9: =DATOS_Logística!F4 -> 4.07 | H9: =DATOS_DataCo!A4 -> First Class | I9: =DATOS_DataCo!B4 -> 8302 | J9: =DATOS_DataCo!C4 -> 0.55 | K9: =DATOS_DataCo!D4 -> 5.15 | L9: =DATOS_DataCo!E4 -> 3.82 | M9: =DATOS_DataCo!F4 -> 2071210.3 | N9: =DATOS_DataCo!G4 -> 3.73
A10: =DATOS_Logística!A5 -> ES | B10: =DATOS_Logística!B5 -> 426 | C10: =DATOS_Logística!C5 -> 0.15 | D10: =DATOS_Logística!D5 -> -5.27 | E10: =DATOS_Logística!E5 -> 9.1 | F10: =DATOS_Logística!F5 -> 4.06 | H10: =DATOS_DataCo!A5 -> Standard Class | I10: =DATOS_DataCo!B5 -> 32973 | J10: =DATOS_DataCo!C5 -> 0.55 | K10: =DATOS_DataCo!D5 -> 5.13 | L10: =DATOS_DataCo!E5 -> 3.83 | M10: =DATOS_DataCo!F5 -> 8033553.1 | N10: =DATOS_DataCo!G5 -> 3.72
A11: =DATOS_Logística!A6 -> SE | B11: =DATOS_Logística!B6 -> 124 | C11: =DATOS_Logística!C6 -> 0.14 | D11: =DATOS_Logística!D6 -> -5.96 | E11: =DATOS_Logística!E6 -> 8.44 | F11: =DATOS_Logística!F6 -> 4.1 | H11: =DATOS_DataCo!A6 -> Second Class | I11: =DATOS_DataCo!B6 -> 10957 | J11: =DATOS_DataCo!C6 -> 0.54 | K11: =DATOS_DataCo!D6 -> 5.11 | L11: =DATOS_DataCo!E6 -> 3.82 | M11: =DATOS_DataCo!F6 -> 2639033.9 | N11: =DATOS_DataCo!G6 -> 3.91
A12: =DATOS_Logística!A7 -> BA | B12: =DATOS_Logística!B7 -> 1407 | C12: =DATOS_Logística!C7 -> 0.13 | D12: =DATOS_Logística!D7 -> -5.46 | E12: =DATOS_Logística!E7 -> 8.93 | F12: =DATOS_Logística!F7 -> 4.06 | H12: =DATOS_DataCo!A7 -> Same Day | I12: =DATOS_DataCo!B7 -> 2768 | J12: =DATOS_DataCo!C7 -> 0.53 | K12: =DATOS_DataCo!D7 -> 5.08 | L12: =DATOS_DataCo!E7 -> 3.84 | M12: =DATOS_DataCo!F7 -> 688212.33 | N12: =DATOS_DataCo!G7 -> 3.63
A13: =DATOS_Logística!A8 -> PA | B13: =DATOS_Logística!B8 -> 428 | C13: =DATOS_Logística!C8 -> 0.13 | D13: =DATOS_Logística!D8 -> -5.66 | E13: =DATOS_Logística!E8 -> 8.71 | F13: =DATOS_Logística!F8 -> 4.07
A14: =DATOS_Logística!A9 -> RS | B14: =DATOS_Logística!B9 -> 2768 | C14: =DATOS_Logística!C9 -> 0.13 | D14: =DATOS_Logística!D9 -> -5.54 | E14: =DATOS_Logística!E9 -> 8.94 | F14: =DATOS_Logística!F9 -> 4.05
A15: =DATOS_Logística!A10 -> GO | B15: =DATOS_Logística!B10 -> 879 | C15: =DATOS_Logística!C10 -> 0.12 | D15: =DATOS_Logística!D10 -> -5.77 | E15: =DATOS_Logística!E10 -> 8.88 | F15: =DATOS_Logística!F10 -> 4.07
A16: =DATOS_Logística!A11 -> SP | B16: =DATOS_Logística!B11 -> 18976 | C16: =DATOS_Logística!C11 -> 0.12 | D16: =DATOS_Logística!D11 -> -5.62 | E16: =DATOS_Logística!E11 -> 8.89 | F16: =DATOS_Logística!F11 -> 4.05
A17: =DATOS_Logística!A12 -> MG | B17: =DATOS_Logística!B12 -> 5508 | C17: =DATOS_Logística!C12 -> 0.12 | D17: =DATOS_Logística!D12 -> -5.61 | E17: =DATOS_Logística!E12 -> 8.9 | F17: =DATOS_Logística!F12 -> 4.07
A18: =DATOS_Logística!A13 -> SC | B18: =DATOS_Logística!B13 -> 1888 | C18: =DATOS_Logística!C13 -> 0.12 | D18: =DATOS_Logística!D13 -> -5.64 | E18: =DATOS_Logística!E13 -> 8.85 | F18: =DATOS_Logística!F13 -> 4.06
A19: =DATOS_Logística!A14 -> PR | B19: =DATOS_Logística!B14 -> 2664 | C19: =DATOS_Logística!C14 -> 0.12 | D19: =DATOS_Logística!D14 -> -5.6 | E19: =DATOS_Logística!E14 -> 8.88 | F19: =DATOS_Logística!F14 -> 4.02
A20: =DATOS_Logística!A15 -> RJ | B20: =DATOS_Logística!B15 -> 5884 | C20: =DATOS_Logística!C15 -> 0.11 | D20: =DATOS_Logística!D15 -> -5.62 | E20: =DATOS_Logística!E15 -> 8.87 | F20: =DATOS_Logística!F15 -> 4.04
A21: =DATOS_Logística!A16 -> PB | B21: =DATOS_Logística!B16 -> 446 | C21: =DATOS_Logística!C16 -> 0.11 | D21: =DATOS_Logística!D16 -> -5.62 | E21: =DATOS_Logística!E16 -> 8.86 | F21: =DATOS_Logística!F16 -> 4.08
A22: =DATOS_Logística!A17 -> RN | B22: =DATOS_Logística!B17 -> 483 | C22: =DATOS_Logística!C17 -> 0.11 | D22: =DATOS_Logística!D17 -> -5.89 | E22: =DATOS_Logística!E17 -> 8.68 | F22: =DATOS_Logística!F17 -> 4.2
A23: =DATOS_Logística!A18 -> MS | B23: =DATOS_Logística!B18 -> 453 | C23: =DATOS_Logística!C18 -> 0.1 | D23: =DATOS_Logística!D18 -> -5.74 | E23: =DATOS_Logística!E18 -> 8.96 | F23: =DATOS_Logística!F18 -> 4.07
A24: =DATOS_Logística!A19 -> CE | B24: =DATOS_Logística!B19 -> 894 | C24: =DATOS_Logística!C19 -> 0.1 | D24: =DATOS_Logística!D19 -> -5.67 | E24: =DATOS_Logística!E19 -> 8.86 | F24: =DATOS_Logística!F19 -> 4.07
... A28: =DATOS_Logística!A23 -> AM | B28: =DATOS_Logística!B23 -> 137 | C28: =DATOS_Logística!C23 -> 0.07 | D28: =DATOS_Logística!D23 -> -6.15 | E28: =DATOS_Logística!E23 -> 8.8 | F28: =DATOS_Logística!F23 -> 4.1

Sheet Tendencia Temporal
A1: EVOLUCIÓN TEMPORAL — Olist E-Commerce + DataCo Supply Chain
A2: Gráficos alimentados directamente desde DATOS_Olist_Mensual (cols C-G, filas 4:29) y DATOS_DataCo (tendencia mensual)

Sheet DATOS_Olist_Mensual
A1: DATOS BASE – OLIST E-COMMERCE (resumen mensual)
A3: Año | B3: Mes | C3: Pedidos | D3: Revenue Total (€) | E3: Ticket Medio (€) | F3: Review Medio | G3: % Tardíos
A4: 2016 | B4: 9 | C4: 2999 | D4: 265051.19 | E4: 76.78 | F4: 4.06 | G4: 0.12
A5: 2016 | B5: 10 | C5: 3319 | D5: 292637.11 | E5: 76.57 | F5: 4.04 | G5: 0.12
A6: 2016 | B6: 11 | C6: 3216 | D6: 279263.9 | E6: 75.56 | F6: 3.99 | G6: 0.12
A7: 2016 | B7: 12 | C7: 3010 | D7: 268911.69 | E7: 77.73 | F7: 4.09 | G7: 0.11
A8: 2017 | B8: 1 | C8: 2830 | D8: 246523.48 | E8: 75.84 | F8: 4.04 | G8: 0.11
A9: 2017 | B9: 2 | C9: 2354 | D9: 209836.67 | E9: 77.48 | F9: 4.05 | G9: 0.11
A10: 2017 | B10: 3 | C10: 2497 | D10: 220533.13 | E10: 76.75 | F10: 4.09 | G10: 0.12
A11: 2017 | B11: 4 | C11: 2276 | D11: 203483.13 | E11: 77.69 | F11: 4.08 | G11: 0.12
A12: 2017 | B12: 5 | C12: 2222 | D12: 192904.16 | E12: 75.58 | F12: 4.1 | G12: 0.11
A13: 2017 | B13: 6 | C13: 1932 | D13: 169172.4 | E13: 76.37 | F13: 4.06 | G13: 0.12
A14: 2017 | B14: 7 | C14: 1930 | D14: 165880.71 | E14: 74.55 | F14: 4.01 | G14: 0.12
A15: 2017 | B15: 8 | C15: 1780 | D15: 158817.43 | E15: 77.53 | F15: 4.1 | G15: 0.12
... A29: 2018 | B29: 10 | C29: 12995 | D29: 1149044.1 | E29: 76.95 | F29: 4.05 | G29: 0.12

Sheet DATOS_Categorías
A1: DATOS BASE – OLIST POR CATEGORÍA DE PRODUCTO
A3: Categoría | B3: Pedidos | C3: Revenue Total (€) | D3: Ticket Medio (€) | E3: Flete Medio (€) | F3: Review Medio | G3: % Tardíos
A4: Eletronicos | B4: 3323 | C4: 302109.4 | D4: 78.91 | E4: 12.01 | F4: 4.04 | G4: 0.12
A5: Livros Tecnicos | B5: 3308 | C5: 301994.9 | D5: 79.43 | E5: 11.86 | F5: 4.05 | G5: 0.13
A6: Musica | B6: 3367 | C6: 300432.59 | D6: 77.6 | E6: 11.62 | F6: 4.06 | G6: 0.12
A7: Relogios Presentes | B7: 3365 | C7: 296836.12 | D7: 76.7 | E7: 11.52 | F7: 4.05 | G7: 0.12
A8: Pet Shop | B8: 3270 | C8: 292351.49 | D8: 77.66 | E8: 11.74 | F8: 4.1 | G8: 0.12
A9: Cama Mesa Banho | B9: 3291 | C9: 291349.63 | D9: 76.97 | E9: 11.56 | F9: 4.05 | G9: 0.12
A10: Bebes | B10: 3261 | C10: 290927.46 | D10: 77.6 | E10: 11.62 | F10: 4.06 | G10: 0.12
A11: Informatica Acessorios | B11: 3331 | C11: 289943.56 | D11: 75.61 | E11: 11.43 | F11: 4.06 | G11: 0.1
A12: Perfumaria | B12: 3251 | C12: 288491.97 | D12: 77.25 | E12: 11.49 | F12: 4.02 | G12: 0.12
A13: Construcao Ferramentas | B13: 3225 | C13: 288174.33 | D13: 77.63 | E13: 11.72 | F13: 4.02 | G13: 0.12
A14: Utilidades Domesticas | B14: 3319 | C14: 287548.46 | D14: 75.35 | E14: 11.29 | F14: 4.04 | G14: 0.12
A15: Ferramentas Jardim | B15: 3220 | C15: 286743.07 | D15: 77.62 | E15: 11.43 | F15: 4.05 | G15: 0.11
... A21: Moveis Decoracao | B21: 3151 | C21: 271931.99 | D21: 75.05 | E21: 11.25 | F21: 4.06 | G21: 0.12

Sheet DATOS_Logística
A1: DATOS BASE – LOGÍSTICA POR ESTADO (pedidos entregados)
A3: Estado | B3: Pedidos | C3: % Tardíos | D3: Retraso Medio (días) | E3: Días Entrega Medio | F3: Review Medio
A4: AL | B4: 260 | C4: 0.15 | D4: -5.72 | E4: 8.69 | F4: 4.07
A5: ES | B5: 426 | C5: 0.15 | D5: -5.27 | E5: 9.1 | F5: 4.06
A6: SE | B6: 124 | C6: 0.14 | D6: -5.96 | E6: 8.44 | F6: 4.1
A7: BA | B7: 1407 | C7: 0.13 | D7: -5.46 | E7: 8.93 | F7: 4.06
A8: PA | B8: 428 | C8: 0.13 | D8: -5.66 | E8: 8.71 | F8: 4.07
A9: RS | B9: 2768 | C9: 0.13 | D9: -5.54 | E9: 8.94 | F9: 4.05
A10: GO | B10: 879 | C10: 0.12 | D10: -5.77 | E10: 8.88 | F10: 4.07
A11: SP | B11: 18976 | C11: 0.12 | D11: -5.62 | E11: 8.89 | F11: 4.05
A12: MG | B12: 5508 | C12: 0.12 | D12: -5.61 | E12: 8.9 | F12: 4.07
A13: SC | B13: 1888 | C13: 0.12 | D13: -5.64 | E13: 8.85 | F13: 4.06
A14: PR | B14: 2664 | C14: 0.12 | D14: -5.6 | E14: 8.88 | F14: 4.02
A15: RJ | B15: 5884 | C15: 0.11 | D15: -5.62 | E15: 8.87 | F15: 4.04
... A23: AM | B23: 137 | C23: 0.07 | D23: -6.15 | E23: 8.8 | F23: 4.1

Sheet DATOS_Pagos_Status
A1: DATOS BASE – MÉTODOS DE PAGO | H1: DATOS BASE – ESTADO DE PEDIDOS
A3: Tipo Pago | B3: Pedidos | C3: Revenue Total (€) | D3: Ticket Medio (€) | E3: Review Medio | F3: Cuotas Medias | H3: Estado Pedido | I3: Pedidos | J3: Revenue Total (€) | K3: Ticket Medio (€)
A4: credit_card | B4: 43378 | C4: 3851876.8 | D4: 77.26 | E4: 4.06 | F4: 5.65 | H4: delivered | I4: 45192 | J4: 4005198.9 | K4: 77.09
A5: boleto | B5: 11311 | C5: 989494.8 | D5: 76.01 | E5: 4.05 | F5: 1 | H5: shipped | I5: 4815 | J5: 424746.62 | K5: 76.68
A6: voucher | B6: 2980 | C6: 261206.39 | D6: 76.1 | E6: 4.07 | F6: 1 | H6: canceled | I6: 3503 | J6: 306739.25 | K6: 76.29
A7: debit_card | B7: 1131 | C7: 97580.96 | D7: 74.96 | E7: 3.95 | F7: 1 | H7: unavailable | I7: 1750 | J7: 148938.12 | K7: 74
H8: processing | I8: 1198 | J8: 107739.62 | K8: 78.22
H9: invoiced | I9: 1192 | J9: 103034.19 | K9: 75.04
H10: approved | I10: 601 | J10: 54981.01 | K10: 79.33
H11: created | I11: 549 | J11: 48781.19 | K11: 77.04

Sheet DATOS_DataCo
A1: DATOS BASE – DATACO SUPPLY CHAIN (modo envío) | I1: DATOS BASE – DATACO POR MERCADO
A3: Modo Envío | B3: Pedidos | C3: % Entrega Tardía | D3: Días Real Medio | E3: Días Prog. Medio | F3: Ventas Totales (€) | G3: Profit Medio (€) | I3: Mercado | J3: Pedidos | K3: Ventas Totales (€) | L3: Descuento Medio | M3: % Entrega Tardía | N3: Profit Medio (€)
A4: First Class | B4: 8302 | C4: 0.55 | D4: 5.15 | E4: 3.82 | F4: 2071210.3 | G4: 3.73 | I4: Europe | J4: 16503 | K4: 4012998.1 | L4: 0.12 | M4: 0.54 | N4: 3.85
A5: Standard Class | B5: 32973 | C5: 0.55 | D5: 5.13 | E5: 3.83 | F5: 8033553.1 | G5: 3.72 | I5: LATAM | J5: 13603 | K5: 3345991 | L5: 0.12 | M5: 0.55 | N5: 3.56
A6: Second Class | B6: 10957 | C6: 0.54 | D6: 5.11 | E6: 3.82 | F6: 2639033.9 | G6: 3.91 | I6: Pacific Asia | J6: 11135 | K6: 2674097.4 | L6: 0.12 | M6: 0.55 | N6: 3.67
A7: Same Day | B7: 2768 | C7: 0.53 | D7: 5.08 | E7: 3.84 | F7: 688212.33 | G7: 3.63 | I7: USCA | J7: 8176 | K7: 2042935.9 | L7: 0.12 | M7: 0.55 | N7: 3.95
I8: Africa | J8: 5583 | K8: 1355987.2 | L8: 0.12 | M8: 0.54 | N8: 3.88
A10: DATOS BASE – DATACO TENDENCIA MENSUAL
A11: Año | B11: Mes | C11: Pedidos | D11: Ventas (€) | E11: % Tardíos
A12: 2015 | B12: 1 | C12: 1142 | D12: 270993.91 | E12: 0.54
A13: 2015 | B13: 2 | C13: 1020 | D13: 255130.77 | E13: 0.55
A14: 2015 | B14: 3 | C14: 1179 | D14: 290334.32 | E14: 0.56
A15: 2015 | B15: 4 | C15: 1146 | D15: 267158.74 | E15: 0.56
A16: 2015 | B16: 5 | C16: 1121 | D16: 270646.13 | E16: 0.54
A17: 2015 | B17: 6 | C17: 1258 | D17: 295562.67 | E17: 0.55
A18: 2015 | B18: 7 | C18: 1180 | D18: 287241.1 | E18: 0.55
A19: 2015 | B19: 8 | C19: 1198 | D19: 285196.47 | E19: 0.54
A20: 2015 | B20: 9 | C20: 1121 | D20: 281518.53 | E20: 0.56
A21: 2015 | B21: 10 | C21: 1163 | D21: 270129.83 | E21: 0.56
A22: 2015 | B22: 11 | C22: 1144 | D22: 283239.43 | E22: 0.54
A23: 2015 | B23: 12 | C23: 1199 | D23: 303294.62 | E23: 0.55
... A59: 2018 | B59: 12 | C59: 1150 | D59: 262601.7 | E59: 0.55
